sqlfaker/__init__.py
sqlfaker/column.py
sqlfaker/database.py
sqlfaker/foreign_key.py
sqlfaker/functions.py
sqlfaker/primary_key.py
sqlfaker/sql_dictionary.py
sqlfaker/table.py
sqlfaker-0.5.dist-info/LICENSE
sqlfaker-0.5.dist-info/METADATA
sqlfaker-0.5.dist-info/WHEEL
sqlfaker-0.5.dist-info/top_level.txt
sqlfaker-0.5.dist-info/RECORD
