Metadata-Version: 2.1
Name: sqlfaker
Version: 0.5
Summary: A fake sql database generator package
Home-page: https://documentation.web.fh-kufstein.ac.at/sqlfaker/
Author: Michael Kohlegger
Author-email: michael.kohlegger@gmail.com
License: UNKNOWN
Platform: UNKNOWN
Classifier: Programming Language :: Python :: 3
Classifier: License :: OSI Approved :: MIT License
Classifier: Operating System :: OS Independent
